atlantis/__init__.py
atlantis/ai/ChatGPT.py
atlantis/ai/FactRetriever.py
atlantis/ai/KnowledgeGraphMemory.py
atlantis/ai/OpenAIWrapper.py
atlantis/ai/__init__.py
atlantis/ai/extract_facts_from_text.py
atlantis/ai/memory/BaseKnowledgeGraphDB.py
atlantis/ai/memory/Fact.py
atlantis/ai/memory/FactsCollection.py
atlantis/ai/memory/KnowledgeGraphDB.py
atlantis/ai/memory/__init__.py
atlantis/ai/memory/db/BaseGraphDB.py
atlantis/ai/memory/db/DuckDBGraphDB.py
atlantis/ai/memory/db/GraphDB.py
atlantis/ai/memory/db/__init__.py
atlantis/ai/memory/graph/BaseGraphBackend.py
atlantis/ai/memory/graph/GraphBackend.py
atlantis/ai/memory/graph/NetworkXGraphBackend.py
atlantis/ai/memory/graph/SimpleGraphBackend.py
atlantis/ai/memory/graph/__init__.py
atlantis/data/__init__.py
atlantis/utils/__init__.py
atlantis/utils/tree.py
atlantis-2025.2.12.2.dist-info/LICENSE
atlantis-2025.2.12.2.dist-info/METADATA
atlantis-2025.2.12.2.dist-info/WHEEL
atlantis-2025.2.12.2.dist-info/top_level.txt
atlantis-2025.2.12.2.dist-info/RECORD
