Metadata-Version: 2.2
Name: atlantis
Version: 2025.2.12.2
Summary: A Python package for automating data analysis and ML model building
Home-page: https://github.com/idin/atlantis
Author: Idin K
Author-email: python@idin.net
License: Conditional Freedom License (CFL-1.0)
Classifier: Programming Language :: Python :: 3
Classifier: License :: Other/Proprietary License
Classifier: Operating System :: OS Independent
Requires-Python: >=3.6
License-File: LICENSE
Requires-Dist: plotly>=5.0.0
Requires-Dist: pandas>=2.0.0
Requires-Dist: numpy>=1.23.5
Dynamic: author
Dynamic: author-email
Dynamic: classifier
Dynamic: description
Dynamic: description-content-type
Dynamic: home-page
Dynamic: license
Dynamic: requires-dist
Dynamic: requires-python
Dynamic: summary
